HiThere/HiThere.py
HiThere/__init__.py
HiThere_vsathyan-0.0.2.dist-info/LICENSE.txt
HiThere_vsathyan-0.0.2.dist-info/METADATA
HiThere_vsathyan-0.0.2.dist-info/WHEEL
HiThere_vsathyan-0.0.2.dist-info/top_level.txt
HiThere_vsathyan-0.0.2.dist-info/RECORD
