Metadata-Version: 2.1
Name: HiThere-vsathyan
Version: 0.0.2
Summary: My first package
Home-page: https://github.com/pypa/sampleproject
Author: Vivek Sathyanarayana
Author-email: vsathyan@stevens.edu
License: UNKNOWN
Platform: UNKNOWN
Classifier: Programming Language :: Python :: 3
Classifier: License :: OSI Approved :: MIT License
Classifier: Operating System :: OS Independent
